    <item>
      <title>Mushroom Coffee Benefits for AI Content Teams</title>
      <link>https://example.com/blog/mushroom-coffee-benefits</link>
      <guid>https://example.com/blog/mushroom-coffee-benefits</guid>
      <pubDate>Mon, 29 Sep 2025 00:00:00 -0000</pubDate>
      <description><![CDATA[Discover how mushroom coffee keeps teams focused with calmer energy rituals and recovery-friendly routines.]]></description>
      <author>Noam Sadi</author>
      <category>ingredient-guides</category>
    </item>
